climate_ref/__init__.py
climate_ref/_config_helpers.py
climate_ref/alembic.ini
climate_ref/config.py
climate_ref/constants.py
climate_ref/database.py
climate_ref/provider_registry.py
climate_ref/py.typed
climate_ref/slurm.py
climate_ref/solver.py
climate_ref/testing.py
climate_ref/cli/__init__.py
climate_ref/cli/_utils.py
climate_ref/cli/config.py
climate_ref/cli/datasets.py
climate_ref/cli/executions.py
climate_ref/cli/providers.py
climate_ref/cli/solve.py
climate_ref/dataset_registry/obs4ref_reference.txt
climate_ref/dataset_registry/sample_data.txt
climate_ref/datasets/__init__.py
climate_ref/datasets/base.py
climate_ref/datasets/cmip6.py
climate_ref/datasets/cmip6_parsers.py
climate_ref/datasets/obs4mips.py
climate_ref/datasets/pmp_climatology.py
climate_ref/datasets/utils.py
climate_ref/executor/__init__.py
climate_ref/executor/hpc.py
climate_ref/executor/local.py
climate_ref/executor/pbs_scheduler.py
climate_ref/executor/result_handling.py
climate_ref/executor/synchronous.py
climate_ref/migrations/README
climate_ref/migrations/env.py
climate_ref/migrations/script.py.mako
climate_ref/migrations/versions/2025-05-02T1418_341a4aa2551e_regenerate.py
climate_ref/migrations/versions/2025-05-09T2032_03dbb4998e49_series_metric_value.py
climate_ref/migrations/versions/2025-07-03T1505_795c1e6cf496_drop_unique_requirement_on_slug.py
climate_ref/migrations/versions/2025-07-20T1521_94beace57a9c_cmip6_finalised.py
climate_ref/migrations/versions/2025-08-05T0327_a1b2c3d4e5f6_finalised_on_base_dataset.py
climate_ref/migrations/versions/2025-09-05T2019_8d28e5e0f9c3_add_indexes.py
climate_ref/migrations/versions/2025-09-10T1358_2f6e36738e06_use_version_as_version_facet_for_.py
climate_ref/migrations/versions/2025-09-22T2359_20cd136a5b04_add_pmp_version.py
climate_ref/models/__init__.py
climate_ref/models/base.py
climate_ref/models/dataset.py
climate_ref/models/diagnostic.py
climate_ref/models/execution.py
climate_ref/models/metric_value.py
climate_ref/models/mixins.py
climate_ref-0.8.1.dist-info/METADATA
climate_ref-0.8.1.dist-info/WHEEL
climate_ref-0.8.1.dist-info/entry_points.txt
climate_ref-0.8.1.dist-info/licenses/LICENCE
climate_ref-0.8.1.dist-info/licenses/NOTICE
climate_ref-0.8.1.dist-info/RECORD
