Metadata-Version: 2.4
Name: climate-ref
Version: 0.8.1
Summary: Application which runs the CMIP Rapid Evaluation Framework
Author-email: Jared Lewis <jared.lewis@climate-resource.com>, Mika Pflueger <mika.pflueger@climate-resource.com>, Bouwe Andela <b.andela@esciencecenter.nl>, Jiwoo Lee <lee1043@llnl.gov>, Min Xu <xum1@ornl.gov>, Nathan Collier <collierno@ornl.gov>, Dora Hegedus <dora.hegedus@stfc.ac.uk>
License-Expression: Apache-2.0
License-File: LICENCE
License-File: NOTICE
Classifier: Development Status :: 3 - Alpha
Classifier: Intended Audience :: Developers
Classifier: Intended Audience :: Science/Research
Classifier: License :: OSI Approved :: Apache Software License
Classifier: Operating System :: MacOS :: MacOS X
Classifier: Operating System :: POSIX :: Linux
Classifier: Programming Language :: Python
Classifier: Programming Language :: Python :: 3
Classifier: Programming Language :: Python :: 3.11
Classifier: Programming Language :: Python :: 3.12
Classifier: Programming Language :: Python :: 3.13
Classifier: Topic :: Scientific/Engineering
Requires-Python: >=3.11
Requires-Dist: alembic>=1.13.3
Requires-Dist: attrs>=24.2.0
Requires-Dist: cattrs>=24.1.2
Requires-Dist: climate-ref-core
Requires-Dist: ecgtools>=2024.7.31
Requires-Dist: environs>=11.0.0
Requires-Dist: loguru>=0.7.2
Requires-Dist: parsl>=2025.5.19; sys_platform != 'win32'
Requires-Dist: platformdirs>=4.3.6
Requires-Dist: sqlalchemy>=2.0.36
Requires-Dist: tomlkit>=0.13.2
Requires-Dist: tqdm>=4.67.1
Requires-Dist: typer>=0.12.5
Provides-Extra: aft-providers
Requires-Dist: climate-ref-esmvaltool>=0.5.0; extra == 'aft-providers'
Requires-Dist: climate-ref-ilamb>=0.5.0; extra == 'aft-providers'
Requires-Dist: climate-ref-pmp>=0.5.0; extra == 'aft-providers'
Provides-Extra: celery
Requires-Dist: climate-ref-celery>=0.5.0; extra == 'celery'
Provides-Extra: postgres
Requires-Dist: alembic-postgresql-enum>=1.7.0; extra == 'postgres'
Requires-Dist: psycopg2-binary>=2.9.2; extra == 'postgres'
Provides-Extra: providers
Requires-Dist: climate-ref-esmvaltool>=0.5.0; extra == 'providers'
Requires-Dist: climate-ref-ilamb>=0.5.0; extra == 'providers'
Requires-Dist: climate-ref-pmp>=0.5.0; extra == 'providers'
